braintrust/__init__.py
braintrust/_generated_types.py
braintrust/audit.py
braintrust/auto.py
braintrust/aws.py
braintrust/bt_json.py
braintrust/conftest.py
braintrust/context.py
braintrust/db_fields.py
braintrust/framework.py
braintrust/framework2.py
braintrust/generated_types.py
braintrust/git_fields.py
braintrust/gitutil.py
braintrust/http_headers.py
braintrust/id_gen.py
braintrust/logger.py
braintrust/merge_row_batch.py
braintrust/oai.py
braintrust/object.py
braintrust/parameters.py
braintrust/prompt.py
braintrust/py.typed
braintrust/queue.py
braintrust/resource_manager.py
braintrust/score.py
braintrust/serializable_data_class.py
braintrust/span_cache.py
braintrust/span_identifier_v1.py
braintrust/span_identifier_v2.py
braintrust/span_identifier_v3.py
braintrust/span_identifier_v4.py
braintrust/span_types.py
braintrust/test_bt_json.py
braintrust/test_context.py
braintrust/test_framework.py
braintrust/test_framework2.py
braintrust/test_helpers.py
braintrust/test_http.py
braintrust/test_id_gen.py
braintrust/test_logger.py
braintrust/test_merge_row_batch.py
braintrust/test_otel.py
braintrust/test_queue.py
braintrust/test_score.py
braintrust/test_serializable_data_class.py
braintrust/test_span_cache.py
braintrust/test_span_components.py
braintrust/test_trace.py
braintrust/test_util.py
braintrust/test_version.py
braintrust/trace.py
braintrust/util.py
braintrust/version.py
braintrust/xact_ids.py
braintrust/cli/__init__.py
braintrust/cli/__main__.py
braintrust/cli/eval.py
braintrust/cli/push.py
braintrust/cli/install/__init__.py
braintrust/cli/install/api.py
braintrust/cli/install/bump_versions.py
braintrust/cli/install/logs.py
braintrust/cli/install/redshift.py
braintrust/cli/install/run_migrations.py
braintrust/contrib/__init__.py
braintrust/contrib/temporal/__init__.py
braintrust/contrib/temporal/test_temporal.py
braintrust/devserver/__init__.py
braintrust/devserver/auth.py
braintrust/devserver/cache.py
braintrust/devserver/cors.py
braintrust/devserver/dataset.py
braintrust-0.5.3.dist-info/METADATA
braintrust-0.5.3.dist-info/WHEEL
braintrust-0.5.3.dist-info/entry_points.txt
braintrust-0.5.3.dist-info/top_level.txt
braintrust-0.5.3.dist-info/RECORD
