Metadata-Version: 2.4
Name: braintrust
Version: 0.5.3
Summary: SDK for integrating Braintrust
Home-page: https://www.braintrust.dev
Author: Braintrust
Author-email: info@braintrust.dev
Project-URL: Source Code, https://github.com/braintrustdata/braintrust-sdk
Project-URL: Bug Tracker, https://github.com/braintrustdata/braintrust-sdk/issues
Classifier: Programming Language :: Python :: 3
Classifier: Programming Language :: Python :: 3.10
Classifier: Operating System :: OS Independent
Requires-Python: >=3.10.0
Requires-Dist: GitPython
Requires-Dist: requests
Requires-Dist: chevron
Requires-Dist: tqdm
Requires-Dist: exceptiongroup>=1.2.0
Requires-Dist: python-dotenv
Requires-Dist: sseclient-py
Requires-Dist: python-slugify
Requires-Dist: typing_extensions>=4.1.0
Requires-Dist: wrapt
Provides-Extra: cli
Requires-Dist: boto3; extra == "cli"
Requires-Dist: psycopg2-binary; extra == "cli"
Requires-Dist: uv; extra == "cli"
Requires-Dist: starlette; extra == "cli"
Requires-Dist: uvicorn; extra == "cli"
Provides-Extra: doc
Requires-Dist: pydoc-markdown; extra == "doc"
Provides-Extra: openai-agents
Requires-Dist: openai-agents; extra == "openai-agents"
Provides-Extra: otel
Requires-Dist: opentelemetry-api; extra == "otel"
Requires-Dist: opentelemetry-sdk; extra == "otel"
Requires-Dist: opentelemetry-exporter-otlp-proto-http; extra == "otel"
Provides-Extra: temporal
Requires-Dist: temporalio>=1.19.0; python_version >= "3.10" and extra == "temporal"
Provides-Extra: all
Requires-Dist: boto3; extra == "all"
Requires-Dist: openai-agents; extra == "all"
Requires-Dist: opentelemetry-api; extra == "all"
Requires-Dist: opentelemetry-exporter-otlp-proto-http; extra == "all"
Requires-Dist: opentelemetry-sdk; extra == "all"
Requires-Dist: psycopg2-binary; extra == "all"
Requires-Dist: pydoc-markdown; extra == "all"
Requires-Dist: starlette; extra == "all"
Requires-Dist: temporalio>=1.19.0; python_version >= "3.10" and extra == "all"
Requires-Dist: uv; extra == "all"
Requires-Dist: uvicorn; extra == "all"
Dynamic: author
Dynamic: author-email
Dynamic: classifier
Dynamic: description
Dynamic: description-content-type
Dynamic: home-page
Dynamic: project-url
Dynamic: provides-extra
Dynamic: requires-dist
Dynamic: requires-python
Dynamic: summary
